esoper/Common.py
esoper/EsOper.py
esoper/__init__.py
EsOper-1.0.0.dist-info/METADATA
EsOper-1.0.0.dist-info/WHEEL
EsOper-1.0.0.dist-info/top_level.txt
EsOper-1.0.0.dist-info/RECORD
