Metadata-Version: 2.1
Name: EsOper
Version: 1.0.0
Summary: Elastic Search Operator by httpx
Home-page: https://github.com/wdf618/ESOper
Author: Dingfeng Wu
Author-email: 94050502@qq.com
License: UNKNOWN
Keywords: Elastic,Elastic Search,httpx
Platform: UNKNOWN
Requires-Python: >=3
Requires-Dist: httpx
